vision_engine/__init__.py
vision_engine/build.py
vision_engine/engine.py
vision_engine/interface.py
vision_engine/main.py
vision_engine/test.py
vision_engine/tracking.py
vision_engine/models/__init__.py
vision_engine/models/build_detector.py
vision_engine/models/build_sam2.py
vision_engine/models/build_tracker.py
vision_engine/models/sam2_camera_predictor.py
vision_engine/utils/__init__.py
vision_engine/utils/bbox_draw.py
vision_engine/utils/logger.py
vision_engine/utils/remote_client.py
vision_engine/utils/unified_drawer.py
vision_rt_engine-0.0.9.data/data/wheels/SAM_2-1.0-cp310-cp310-linux_x86_64.whl
vision_rt_engine-0.0.9.dist-info/METADATA
vision_rt_engine-0.0.9.dist-info/WHEEL
vision_rt_engine-0.0.9.dist-info/top_level.txt
vision_rt_engine-0.0.9.dist-info/zip-safe
vision_rt_engine-0.0.9.dist-info/RECORD
