Metadata-Version: 2.4
Name: vision_rt_engine
Version: 0.0.9
Author: Krishneel
License: MIT
Classifier: Development Status :: 4 - Beta
Classifier: Intended Audience :: Developers
Classifier: Topic :: Software Development :: Build Tools
Classifier: License :: OSI Approved :: MIT License
Classifier: Programming Language :: Python :: 3
Classifier: Programming Language :: Python :: 3.9
Classifier: Programming Language :: Python :: 3.10
Classifier: Programming Language :: Python :: 3.11
Requires-Dist: numpy
Requires-Dist: matplotlib
Requires-Dist: opencv-python>=4.4
Requires-Dist: pillow
Requires-Dist: torch>=2.0
Requires-Dist: torchvision
Requires-Dist: tqdm
Requires-Dist: pytest
Requires-Dist: igniter>=1.0.6
Provides-Extra: full
Provides-Extra: dev
Requires-Dist: jupyterlab; extra == "dev"
Dynamic: author
Dynamic: classifier
Dynamic: license
Dynamic: provides-extra
Dynamic: requires-dist
